.gitignore
MANIFEST.in
README.txt
setup.py
IssueTrackerMassContainer/CHANGES.txt
IssueTrackerMassContainer/Constants.py
IssueTrackerMassContainer/MassContainer.py
IssueTrackerMassContainer/RecentActivity.py
IssueTrackerMassContainer/Utils.py
IssueTrackerMassContainer/__init__.py
IssueTrackerMassContainer/refresh.txt
IssueTrackerMassContainer/tags
IssueTrackerMassContainer/version.txt
IssueTrackerMassContainer/css/jquery.treeview.css
IssueTrackerMassContainer/dtml/AllrecentIssues.dtml
IssueTrackerMassContainer/dtml/index_html.dtml
IssueTrackerMassContainer/dtml/masscontainer_style.css.dtml
IssueTrackerMassContainer/dtml/standard_html_footer.dtml
IssueTrackerMassContainer/dtml/standard_html_header.dtml
IssueTrackerMassContainer/dtml/trackersOfInterestForm.dtml
IssueTrackerMassContainer/js/core.js
IssueTrackerMassContainer/js/jquery-1.3.2.min.js
IssueTrackerMassContainer/js/jquery.cookie.js
IssueTrackerMassContainer/js/jquery.treeview.min.js
IssueTrackerMassContainer/standards/automate.py
IssueTrackerMassContainer/standards/favicon.ico
IssueTrackerMassContainer/www/file.gif
IssueTrackerMassContainer/www/folder-closed.gif
IssueTrackerMassContainer/www/folder.gif
IssueTrackerMassContainer/www/gradissuehead.png
IssueTrackerMassContainer/www/gradtablehead.png
IssueTrackerMassContainer/www/icon_ignore.gif
IssueTrackerMassContainer/www/issuetrackermasscontainer.gif
IssueTrackerMassContainer/www/loading-arrows.gif
IssueTrackerMassContainer/www/loading-bar.gif
IssueTrackerMassContainer/www/minus.gif
IssueTrackerMassContainer/www/plus.gif
IssueTrackerMassContainer/www/refresh_icon.png
IssueTrackerMassContainer/www/rss-blue.png
IssueTrackerMassContainer/www/treeview-black-line.gif
IssueTrackerMassContainer/www/treeview-black.gif
IssueTrackerMassContainer/www/treeview-default-line.gif
IssueTrackerMassContainer/www/treeview-default.gif
IssueTrackerMassContainer/www/treeview-famfamfam-line.gif
IssueTrackerMassContainer/www/treeview-famfamfam.gif
IssueTrackerProduct.egg-info/PKG-INFO
IssueTrackerProduct.egg-info/SOURCES.txt
IssueTrackerProduct.egg-info/dependency_links.txt
IssueTrackerProduct.egg-info/not-zip-safe
IssueTrackerProduct.egg-info/requires.txt
IssueTrackerProduct.egg-info/top_level.txt
