Metadata-Version: 1.1
Name: IssueTrackerProduct
Version: 0.14.2.dev0
Summary: Bug/issue tracker for Zope2.
Home-page: https://github.com/sureshvv/IsssueTrackerProduct
Author: Peter Bengtsson
Author-email: mail@peterbe.com
License: GPL
Keywords: Zope tracker issue bug
Platform: UNKNOWN
Classifier: Framework :: Zope2
Classifier: Programming Language :: Python
